kgegrok/__init__.py
kgegrok/cli.py
kgegrok/estimate.py
kgegrok/evaluation.py
kgegrok/models.py
kgegrok/text_models.py
kgegrok/utils.py
kgegrok/data/__init__.py
kgegrok/data/constants.py
kgegrok/data/statstools.py
kgegrok/data/transformers.py
kgegrok/stats/__init__.py
kgegrok/stats/constants.py
kgegrok/tests/__init__.py
kgegrok/tests/data_statstools_test.py
kgegrok/tests/data_transformers_test.py
kgegrok/tests/stats_test.py
kgegrok/tests/test_data.py
kgegrok-0.5.0.dist-info/METADATA
kgegrok-0.5.0.dist-info/WHEEL
kgegrok-0.5.0.dist-info/top_level.txt
kgegrok-0.5.0.dist-info/RECORD
