Metadata-Version: 2.1
Name: kgegrok
Version: 0.5.0
Summary: knowledge representation learning
Home-page: http://github.com/fantasticfears/kgegrok
Author: Erick Guan
Author-email: fantasticfears@gmail.com
License: GPLv2
Platform: UNKNOWN
Classifier: Development Status :: 4 - Beta
Classifier: License :: OSI Approved :: GNU General Public License v2 (GPLv2)
Classifier: Intended Audience :: Developers
Classifier: Programming Language :: Python :: 3
Requires-Dist: kgekit
Requires-Dist: numpy (>=1.10)
Requires-Dist: torch (>=1.0)
